README
setup.py
pyCMM/__init__.py
pyCMM/app.py
pyCMM/mylib.py
pyCMM/settings.py
pyCMM/template.py
pyCMM.egg-info/PKG-INFO
pyCMM.egg-info/SOURCES.txt
pyCMM.egg-info/dependency_links.txt
pyCMM.egg-info/top_level.txt
pyCMM/app/__init__.py
pyCMM/app/app.py