Metadata-Version: 1.0
Name: pyCMM
Version: 0.0.2
Summary: further linkage analysis
Home-page: http://pypi.python.org/pypi/pyCMM/
Author: Jessada Thutkawkorapin
Author-email: jessada.thutkawkorapin@gmail.com
License: LICENSE.txt
Platform: UNKNOWN
